carla/__init__.py
carla/command.pyi
carla/libcarla.cp310-win_amd64.pyd
carla/libcarla.pyi
carla-0.9.16.dist-info/METADATA
carla-0.9.16.dist-info/WHEEL
carla-0.9.16.dist-info/top_level.txt
carla-0.9.16.dist-info/RECORD
