Metadata-Version: 2.4
Name: carla
Version: 0.9.16
Summary: Python API for communicating with the CARLA server.
Home-page: https://github.com/carla-simulator/carla
Author: The CARLA team
Author-email: carla.simulator@gmail.com
License: MIT License
Dynamic: author
Dynamic: author-email
Dynamic: description
Dynamic: description-content-type
Dynamic: home-page
Dynamic: license
Dynamic: summary
